{
    "variables": {},
	   "steps": {
        "100": {"type": "os", "name": "df test", "dependencies": [], "task": "df -h"}, 
        "200": {
      		"type": "os",
      		"task": "python step1.py",
            "name": "step 200", 
            "dependencies": []
        }, 
        "300": {
      		"type": "os",
      		"task": "python step2.py",
            "name": "step 300", 
            "dependencies": []
        }, 
        "400": {
      		"type": "os",
      		"task": "python step2.py", 
            "name": "be creative here", 
            "dependencies": ["100"]
        },
        "500": {
            "type": "os",
			"task": "ls -alh", 
            "name": "ls_test", 
            "dependencies": ["100","300"]
        },	
        "600": {
			"type": "os",
            "task": "date", 
            "name": "date test", 
            "dependencies": []
        },			
        "9999": {
      			"type": "internal",
      			"task": "send_mail",
            "name": "job_complete", 
      			"dependencies": "ALL",
      			"detail": {
                      "mail_to": "someone@somewhere.com",
              				"mail_from": "job_control@somewhere.com",
              				"mail_subject": "Job job1.conf.json complete",
              				"mail_body": ""
              			}
             }		
    }
}
